{"display":{"gui":{"translation":[24,24,24]},"head":{"scale":[4,4,4],"translation":[80,73.6,80]}},"elements":[{"faces":{"down":{"texture":"#0","uv":[12.75,3.4375,12.25,3.75]},"east":{"texture":"#0","uv":[11.625,3.75,11.9375,3.9375]},"north":{"texture":"#0","uv":[11.9375,3.9375,12.4375,4.125]},"south":{"texture":"#0","uv":[12.5625,3.75,12.875,3.9375]},"up":{"texture":"#0","uv":[12.25,3.75,11.9375,3.4375]},"west":{"texture":"#0","uv":[12.25,3.75,12.5625,3.9375]}},"from":[-16,-16,-16],"shade":false,"to":[-12.808001,-14.807999,-14.007998]}],"overrides":[],"textures":{"0":"item/w1539508421_1"}}