{"display":{"head":{"scale":[4,4,4],"translation":[-16,-22.4,-16]}},"elements":[{"faces":{"down":{"texture":"#0","uv":[2.625,4,4.5,6.625]},"east":{"texture":"#0","uv":[7.125,7.125,4.5,6.625]},"north":{"texture":"#0","uv":[4.5,7.125,2.625,6.625]},"south":{"texture":"#0","uv":[9,7.125,7.125,6.625]},"up":{"texture":"#0","uv":[4.5,6.625,6.375,4]},"west":{"texture":"#0","uv":[2.625,7.125,0,6.625]}},"from":[8,8,8],"shade":false,"to":[13.6,6.4,16.4]}],"overrides":[],"textures":{"0":"item/w175722239_0"}}